{
  "1": {
    "id": 1,
    "abilityName": "Melee Auto Attack",
    "abilityImage": "/images/combat/ability_icons/basic_melee.png",
    "description": "A basic melee auto attack",
    "damageType": "Melee",
    "damageScaling": [
      {
        "affinity": "Melee",
        "scaling": 1
      }
    ],
    "accuracyScaling": [
      {
        "affinity": "Melee",
        "scaling": 1
      }
    ],
    "baseSpeedCoeff": 1,
    "baseMinimumDamageCoeff": 1,
    "baseMaximumDamageCoeff": 1,
    "baseAccuracyCoeff": 1,
    "maxTargets": 1
  },
  "2": {
    "id": 2,
    "abilityName": "Magic Auto Attack",
    "abilityImage": "/images/combat/ability_icons/basic_magic.png",
    "description": "A basic magic auto attack",
    "damageType": "Magic",
    "damageScaling": [
      {
        "affinity": "Magic",
        "scaling": 1
      }
    ],
    "accuracyScaling": [
      {
        "affinity": "Magic",
        "scaling": 1
      }
    ],
    "baseSpeedCoeff": 1,
    "baseMinimumDamageCoeff": 1,
    "baseMaximumDamageCoeff": 1,
    "baseAccuracyCoeff": 1,
    "maxTargets": 1
  },
  "3": {
    "id": 3,
    "abilityName": "Range Auto Attack",
    "abilityImage": "/images/combat/ability_icons/basic_range.png",
    "description": "A basic range auto attack",
    "damageType": "Range",
    "damageScaling": [
      {
        "affinity": "Range",
        "scaling": 1
      }
    ],
    "accuracyScaling": [
      {
        "affinity": "Range",
        "scaling": 1
      }
    ],
    "baseSpeedCoeff": 1,
    "baseMinimumDamageCoeff": 1,
    "baseMaximumDamageCoeff": 1,
    "baseAccuracyCoeff": 1,
    "maxTargets": 1
  },
  "4": {
    "id": 4,
    "abilityName": "Slash",
    "abilityImage": "/images/combat/ability_icons/cleave.png",
    "description": "A basic melee slash",
    "damageType": "Melee",
    "damageScaling": [
      {
        "affinity": "Melee",
        "scaling": 1
      },
      {
        "affinity": "Slashing",
        "scaling": 1.333
      }
    ],
    "accuracyScaling": [
      {
        "affinity": "Melee",
        "scaling": 1
      },
      {
        "affinity": "Slashing",
        "scaling": 1.333
      }
    ],
    "baseSpeedCoeff": 1,
    "baseMinimumDamageCoeff": 1,
    "baseMaximumDamageCoeff": 1,
    "baseAccuracyCoeff": 1,
    "maxTargets": 1
  },
  "5": {
    "id": 5,
    "abilityName": "Stab",
    "abilityImage": "/images/combat/ability_icons/stab.png",
    "description": "A basic melee stab",
    "damageType": "Melee",
    "damageScaling": [
      {
        "affinity": "Melee",
        "scaling": 1
      },
      {
        "affinity": "Piercing",
        "scaling": 1.333
      }
    ],
    "accuracyScaling": [
      {
        "affinity": "Melee",
        "scaling": 1
      },
      {
        "affinity": "Piercing",
        "scaling": 1.333
      }
    ],
    "baseSpeedCoeff": 1,
    "baseMinimumDamageCoeff": 1,
    "baseMaximumDamageCoeff": 1,
    "baseAccuracyCoeff": 1,
    "maxTargets": 1
  },
  "6": {
    "id": 6,
    "abilityName": "Crush",
    "abilityImage": "/images/combat/ability_icons/crush.png",
    "description": "A basic melee crush",
    "damageType": "Melee",
    "damageScaling": [
      {
        "affinity": "Melee",
        "scaling": 1
      },
      {
        "affinity": "Blunt",
        "scaling": 1.333
      }
    ],
    "accuracyScaling": [
      {
        "affinity": "Melee",
        "scaling": 1
      },
      {
        "affinity": "Blunt",
        "scaling": 1.333
      }
    ],
    "baseSpeedCoeff": 1,
    "baseMinimumDamageCoeff": 1,
    "baseMaximumDamageCoeff": 1,
    "baseAccuracyCoeff": 1,
    "maxTargets": 1
  },
  "7": {
    "id": 7,
    "abilityName": "Fire Ball",
    "abilityImage": "/images/combat/ability_icons/fireball.png",
    "description": "A ball of flames",
    "damageType": "Magic",
    "damageScaling": [
      {
        "affinity": "Magic",
        "scaling": 1
      },
      {
        "affinity": "Fire",
        "scaling": 1.333
      }
    ],
    "accuracyScaling": [
      {
        "affinity": "Magic",
        "scaling": 1
      },
      {
        "affinity": "Fire",
        "scaling": 1.333
      }
    ],
    "baseSpeedCoeff": 1.2,
    "baseMinimumDamageCoeff": 1,
    "baseMaximumDamageCoeff": 1,
    "baseAccuracyCoeff": 1,
    "maxTargets": 1
  },
  "8": {
    "id": 8,
    "abilityName": "Ice Shard",
    "abilityImage": "/images/combat/ability_icons/ice_shard.png",
    "description": "A piercing shard of ice",
    "damageType": "Magic",
    "damageScaling": [
      {
        "affinity": "Magic",
        "scaling": 1
      },
      {
        "affinity": "Piercing",
        "scaling": 1.1
      },
      {
        "affinity": "Ice",
        "scaling": 1.333
      }
    ],
    "accuracyScaling": [
      {
        "affinity": "Magic",
        "scaling": 1
      },
      {
        "affinity": "Piercing",
        "scaling": 1.1
      },
      {
        "affinity": "Ice",
        "scaling": 1.333
      }
    ],
    "baseSpeedCoeff": 1.2,
    "baseMinimumDamageCoeff": 1,
    "baseMaximumDamageCoeff": 1,
    "baseAccuracyCoeff": 1,
    "maxTargets": 1
  },
  "9": {
    "id": 9,
    "abilityName": "Nature's Sanctuary",
    "abilityImage": "/images/combat/ability_icons/reinforce.png",
    "description": "A defensive nature spell",
    "damageType": "Magic",
    "damageScaling": [
      {
        "affinity": "Magic",
        "scaling": 1
      },
      {
        "affinity": "Nature",
        "scaling": 1.333
      }
    ],
    "accuracyScaling": [
      {
        "affinity": "Magic",
        "scaling": 1
      },
      {
        "affinity": "Nature",
        "scaling": 1.333
      }
    ],
    "baseSpeedCoeff": 1.2,
    "baseMinimumDamageCoeff": 0.25,
    "baseMaximumDamageCoeff": 0.5,
    "baseAccuracyCoeff": 1.5,
    "maxTargets": 1
  }
}